esm_analysis/__init__.py
esm_analysis/cli.py
esm_analysis/esm_analysis.py
esm_analysis/logfile.py
esm_analysis/components/__init__.py
esm_analysis/components/echam.py
esm_analysis/components/fesom.py
esm_analysis/scripts/__init__.py
esm_analysis/scripts/analysis_scripts/__init__.py
esm_analysis/scripts/analysis_scripts/fesom/ANALYSIS_fesom_sfc_timmean.py
esm_analysis/scripts/analysis_scripts/fesom/ANALYSIS_fesom_sfc_timseries.py
esm_analysis/scripts/analysis_scripts/fesom/__init__.py
esm_analysis/scripts/analysis_scripts/fesom/calculate_FESOM_MOC.py
tests/__init__.py
tests/test_esm_analysis.py
esm_analysis-0.4.2.dist-info/AUTHORS.rst
esm_analysis-0.4.2.dist-info/LICENSE
esm_analysis-0.4.2.dist-info/METADATA
esm_analysis-0.4.2.dist-info/WHEEL
esm_analysis-0.4.2.dist-info/dependency_links.txt
esm_analysis-0.4.2.dist-info/entry_points.txt
esm_analysis-0.4.2.dist-info/top_level.txt
esm_analysis-0.4.2.dist-info/RECORD
