Metadata-Version: 2.1
Name: esm-analysis
Version: 0.4.2
Summary: Analysis Scripts for ESM Simulations
Home-page: https://github.com/pgierz/esm_analysis
Author: Paul Gierz
Author-email: pgierz@awi.de
License: GNU General Public License v3
Keywords: esm_analysis
Platform: UNKNOWN
Classifier: Development Status :: 2 - Pre-Alpha
Classifier: Intended Audience :: Developers
Classifier: License :: OSI Approved :: GNU General Public License v3 (GPLv3)
Classifier: Natural Language :: English
Classifier: Programming Language :: Python :: 2
Classifier: Programming Language :: Python :: 2.7
Classifier: Programming Language :: Python :: 3
Classifier: Programming Language :: Python :: 3.4
Classifier: Programming Language :: Python :: 3.5
Classifier: Programming Language :: Python :: 3.6
Classifier: Programming Language :: Python :: 3.7
Requires-Dist: cdo
Requires-Dist: Click (>=6.0)
Requires-Dist: pandas
Requires-Dist: tabulate
Requires-Dist: regex-engine
Requires-Dist: pyyaml
